services_communication/__init__.py
services_communication/apps.py
services_communication/broker.py
services_communication/defaults.py
services_communication/error.py
services_communication/models.py
services_communication/publishing_backend.py
services_communication/settings.py
services_communication/types.py
services_communication/utils.py
services_communication/call/__init__.py
services_communication/call/call.py
services_communication/call/command.py
services_communication/consumer/__init__.py
services_communication/management/__init__.py
services_communication/management/commands/__init__.py
services_communication/management/commands/checkpublisher.py
services_communication/management/commands/devconsumer.py
services_communication/management/commands/devpublisher.py
services_communication/management/commands/runconsumer.py
services_communication/management/commands/runpublisher.py
services_communication/migrations/0001_initial.py
services_communication/migrations/0002_publishedeventqueue_create_time_and_more.py
services_communication/migrations/0003_publishedeventqueue_body_and_more.py
services_communication/migrations/0004_publishedeventqueue_add_trigger.py
services_communication/migrations/0005_publishedeventqueue_rename_chanel_20250313_0733.py
services_communication/migrations/0006_publishedeventqueue_properties.py
services_communication/migrations/__init__.py
services_communication/process/__init__.py
services_communication/process/consumer.py
services_communication/process/publisher.py
services_communication/publisher/__init__.py
services_communication/publisher/events.py
services_communication/publisher/queue_handler.py
services_communication/rest_api/__init__.py
services_communication/rest_api/auth_helper.py
services_communication/rest_api/client_api_helper.py
services_communication/rest_api/error.py
services_communication/rest_api/formatter.py
services_communication/rest_api/utils.py
services_communication/routing/__init__.py
django_microservices_communication-2.6.9.dist-info/METADATA
django_microservices_communication-2.6.9.dist-info/WHEEL
django_microservices_communication-2.6.9.dist-info/top_level.txt
django_microservices_communication-2.6.9.dist-info/RECORD
