Metadata-Version: 2.4
Name: django-microservices-communication
Version: 2.6.9
Summary: Pub/Sub for microservice on django
Home-page: https://github.com/ksinn/django-microservices-communication
Author: ksinn
Author-email: ksinnd@gmail.com
Requires-Dist: Django
Requires-Dist: djangorestframework
Requires-Dist: djangorestframework-camel-case
Requires-Dist: pika
Requires-Dist: requests
Requires-Dist: pytz
Dynamic: author
Dynamic: author-email
Dynamic: description
Dynamic: description-content-type
Dynamic: home-page
Dynamic: requires-dist
Dynamic: summary
